gitlab_api/__init__.py
gitlab_api/__main__.py
gitlab_api/decorators.py
gitlab_api/exceptions.py
gitlab_api/gitlab_agent.py
gitlab_api/gitlab_api.py
gitlab_api/gitlab_gql.py
gitlab_api/gitlab_input_models.py
gitlab_api/gitlab_mcp.py
gitlab_api/gitlab_response_models.py
gitlab_api/mcp_config.json
gitlab_api/middlewares.py
gitlab_api/utils.py
gitlab_api/skills/gitlab-branches/SKILL.md
gitlab_api/skills/gitlab-commits/SKILL.md
gitlab_api/skills/gitlab-custom-api/SKILL.md
gitlab_api/skills/gitlab-deploy-tokens/SKILL.md
gitlab_api/skills/gitlab-environments/SKILL.md
gitlab_api/skills/gitlab-groups/SKILL.md
gitlab_api/skills/gitlab-jobs/SKILL.md
gitlab_api/skills/gitlab-members/SKILL.md
gitlab_api/skills/gitlab-merge-requests/SKILL.md
gitlab_api/skills/gitlab-merge-rules/SKILL.md
gitlab_api/skills/gitlab-packages/SKILL.md
gitlab_api/skills/gitlab-pipeline-schedules/SKILL.md
gitlab_api/skills/gitlab-pipelines/SKILL.md
gitlab_api/skills/gitlab-projects/SKILL.md
gitlab_api/skills/gitlab-protected-branches/SKILL.md
gitlab_api/skills/gitlab-releases/SKILL.md
gitlab_api/skills/gitlab-runners/SKILL.md
gitlab_api/skills/gitlab-tags/SKILL.md
gitlab_api-25.14.17.dist-info/licenses/LICENSE
scripts/validate_a2a_agent.py
scripts/validate_agent.py
tests/test_gitlab_a2a_validation.py
tests/test_gitlab_api.py
tests/test_gitlab_mcp_validation.py
tests/test_gitlab_models.py
tests/test_utils.py
tests/test_verify_agent.py
tests/verify_a2a_queries.py
gitlab_api-25.14.17.dist-info/METADATA
gitlab_api-25.14.17.dist-info/WHEEL
gitlab_api-25.14.17.dist-info/entry_points.txt
gitlab_api-25.14.17.dist-info/top_level.txt
gitlab_api-25.14.17.dist-info/RECORD
